plover_german_syllatype/__init__.py
plover_german_syllatype/dictionary.py
plover_german_syllatype/system.py
plover_german_syllatype-1.3.1.dist-info/METADATA
plover_german_syllatype-1.3.1.dist-info/WHEEL
plover_german_syllatype-1.3.1.dist-info/entry_points.txt
plover_german_syllatype-1.3.1.dist-info/top_level.txt
plover_german_syllatype-1.3.1.dist-info/zip-safe
plover_german_syllatype-1.3.1.dist-info/RECORD
