Metadata-Version: 2.1
Name: plover-german-syllatype
Version: 1.3.1
Summary: German Syllatype Layout for Plover
Author: delta, Kaoffie
Keywords: plover plover_plugin
Classifier: Development Status :: 4 - Beta
Classifier: Environment :: Plugins
Classifier: Intended Audience :: End Users/Desktop
Classifier: Operating System :: OS Independent
Classifier: Programming Language :: Python :: 3
Classifier: Programming Language :: Python :: 3.6
